{"stats":{"minecraft:used":{"minecraft:bread":2,"minecraft:white_bed":1},"minecraft:crafted":{"minecraft:oak_planks":16,"minecraft:crafting_table":1},"minecraft:mined":{"minecraft:potatoes":3,"minecraft:oak_log":4,"minecraft:white_bed":1,"minecraft:carrots":7,"minecraft:wheat":5},"minecraft:custom":{"minecraft:time_since_rest":6473,"minecraft:open_chest":3,"minecraft:play_one_minute":9006,"minecraft:crouch_one_cm":2646,"minecraft:sprint_one_cm":48673,"minecraft:damage_taken":25,"minecraft:walk_one_cm":27477,"minecraft:sneak_time":636,"minecraft:jump":202,"minecraft:time_since_death":9006,"minecraft:sleep_in_bed":1,"minecraft:fall_one_cm":4478,"minecraft:fly_one_cm":54782},"minecraft:picked_up":{"minecraft:wheat":1,"minecraft:wheat_seeds":6,"minecraft:potato":6,"minecraft:oak_log":4,"minecraft:bread":2,"minecraft:white_bed":1,"minecraft:carrot":16}},"DataVersion":2586}